{"ok":true,"rows":[{"jsonc":[{"type":"C","position":"0","column_name":"a_name"},{"type":"N","position":"1","column_name":"target_q1","digit_number":0,"is_show":1,"is_chart":0,"sum_type":"SUM"},{"type":"N","position":"2","column_name":"target1_q1","digit_number":0,"is_show":1,"is_chart":0,"sum_type":"SUM"},{"type":"F","column_name":"F3","position":"3","formula":"(#{target1_q1}/#{target_q1})*100","formula_old":"(,2,/,1,),*rate","digit_number":2,"number_format":1,"is_chart":0,"bgcolor":"#98fbfa","sum_type":"SUM"},{"type":"N","position":"4","column_name":"result1_q1","digit_number":0,"is_show":1,"is_chart":0,"sum_type":"SUM"},{"type":"F","column_name":"F5","position":"5","formula":"(#{result1_q1}/#{target1_q1})*100","formula_old":"(,4,/,2,),*rate","digit_number":2,"number_format":1,"is_chart":0,"bgcolor":"#fbc198","sum_type":"SUM"},{"type":"N","position":"6","column_name":"result2_q1","digit_number":0,"is_show":1,"is_chart":0,"sum_type":"SUM"},{"type":"F","column_name":"F7","position":"7","formula":"(#{result2_q1}/#{target1_q1})*100","formula_old":"(,6,/,2,),*rate","digit_number":2,"number_format":1,"is_chart":0,"bgcolor":"#fbfa98","sum_type":"SUM"},{"type":"N","position":"8","column_name":"result3_q1","digit_number":0,"is_show":1,"is_chart":0,"sum_type":"SUM"},{"type":"F","column_name":"F9","position":"9","formula":"(#{result3_q1}/#{target1_q1})*100","formula_old":"(,8,/,2,),*rate","digit_number":2,"number_format":1,"is_chart":1,"bgcolor":"#50B432","sum_type":"SUM"},{"type":"N","position":"10","column_name":"result4_q1","digit_number":0,"is_show":1,"is_chart":0,"sum_type":"SUM"},{"type":"F","column_name":"F11","position":"11","formula":"(#{result4_q1}/#{target1_q1})*100","formula_old":"(,10,/,2,),*rate","digit_number":2,"number_format":1,"is_chart":0,"bgcolor":"#fbfa98","sum_type":"SUM"},{"type":"N","position":"12","column_name":"result5_q1","digit_number":0,"is_show":1,"is_chart":0,"sum_type":"SUM"},{"type":"F","column_name":"F13","position":"13","formula":"(#{result5_q1}/#{target1_q1})*100","formula_old":"(,12,/,2,),*rate","digit_number":2,"number_format":1,"is_chart":0,"bgcolor":"#fbc198","sum_type":"SUM"},{"type":"N","position":"14","column_name":"target_q2","digit_number":0,"is_show":1,"is_chart":0,"sum_type":"SUM"},{"type":"N","position":"15","column_name":"target1_q2","digit_number":0,"is_show":1,"is_chart":0,"sum_type":"SUM"},{"type":"F","column_name":"F16","position":"16","formula":"(#{target1_q2}/#{target_q2})*100","formula_old":"(,15,/,14,),*rate","digit_number":2,"number_format":1,"is_chart":0,"bgcolor":"#98fbfa","sum_type":"SUM"},{"type":"N","position":"17","column_name":"result1_q2","digit_number":0,"is_show":1,"is_chart":0,"sum_type":"SUM"},{"type":"F","column_name":"F18","position":"18","formula":"(#{result1_q2}/#{target1_q2})*100","formula_old":"(,17,/,15,),*rate","digit_number":2,"number_format":1,"is_chart":0,"bgcolor":"#fbc198","sum_type":"SUM"},{"type":"N","position":"19","column_name":"result2_q2","digit_number":0,"is_show":1,"is_chart":0,"sum_type":"SUM"},{"type":"F","column_name":"F20","position":"20","formula":"(#{result2_q2}/#{target1_q2})*100","formula_old":"(,19,/,15,),*rate","digit_number":2,"number_format":1,"is_chart":0,"bgcolor":"#fbfa98","sum_type":"SUM"},{"type":"N","position":"21","column_name":"result3_q2","digit_number":0,"is_show":1,"is_chart":0,"sum_type":"SUM"},{"type":"F","column_name":"F22","position":"22","formula":"(#{result3_q2}/#{target1_q2})*100","formula_old":"(,21,/,15,),*rate","digit_number":2,"number_format":1,"is_chart":1,"bgcolor":"#50B432","sum_type":"SUM"},{"type":"N","position":"23","column_name":"result4_q2","digit_number":0,"is_show":1,"is_chart":0,"sum_type":"SUM"},{"type":"F","column_name":"F24","position":"24","formula":"(#{result4_q2}/#{target1_q2})*100","formula_old":"(,23,/,15,),*rate","digit_number":2,"number_format":1,"is_chart":0,"bgcolor":"#fbfa98","sum_type":"SUM"},{"type":"N","position":"25","column_name":"result5_q2","digit_number":0,"is_show":1,"is_chart":0,"sum_type":"SUM"},{"type":"F","column_name":"F26","position":"26","formula":"(#{result5_q2}/#{target1_q2})*100","formula_old":"(,25,/,15,),*rate","digit_number":2,"number_format":1,"is_chart":0,"bgcolor":"#fbc198","sum_type":"SUM"},{"type":"N","position":"27","column_name":"target_q3","digit_number":0,"is_show":1,"is_chart":0,"sum_type":"SUM"},{"type":"N","position":"28","column_name":"target1_q3","digit_number":0,"is_show":1,"is_chart":0,"sum_type":"SUM"},{"type":"F","column_name":"F29","position":"29","formula":"(#{target1_q3}/#{target_q3})*100","formula_old":"(,28,/,27,),*rate","digit_number":2,"number_format":1,"is_chart":0,"bgcolor":"#98fbfa","sum_type":"SUM"},{"type":"N","position":"30","column_name":"result1_q3","digit_number":0,"is_show":1,"is_chart":0,"sum_type":"SUM"},{"type":"F","column_name":"F31","position":"31","formula":"(#{result1_q3}/#{target1_q3})*100","formula_old":"(,30,/,28,),*rate","digit_number":2,"number_format":1,"is_chart":0,"bgcolor":"#fbc198","sum_type":"SUM"},{"type":"N","position":"32","column_name":"result2_q3","digit_number":0,"is_show":1,"is_chart":0,"sum_type":"SUM"},{"type":"F","column_name":"F33","position":"33","formula":"(#{result2_q3}/#{target1_q3})*100","formula_old":"(,32,/,28,),*rate","digit_number":2,"number_format":1,"is_chart":0,"bgcolor":"#fbfa98","sum_type":"SUM"},{"type":"N","position":"34","column_name":"result3_q3","digit_number":0,"is_show":1,"is_chart":0,"sum_type":"SUM"},{"type":"F","column_name":"F35","position":"35","formula":"(#{result3_q3}/#{target1_q3})*100","formula_old":"(,34,/,28,),*rate","digit_number":2,"number_format":1,"is_chart":1,"bgcolor":"#50B432","sum_type":"SUM"},{"type":"N","position":"36","column_name":"result4_q3","digit_number":0,"is_show":1,"is_chart":0,"sum_type":"SUM"},{"type":"F","column_name":"F37","position":"37","formula":"(#{result4_q3}/#{target1_q3})*100","formula_old":"(,36,/,28,),*rate","digit_number":2,"number_format":1,"is_chart":0,"bgcolor":"#fbfa98","sum_type":"SUM"},{"type":"N","position":"38","column_name":"result5_q3","digit_number":0,"is_show":1,"is_chart":0,"sum_type":"SUM"},{"type":"F","column_name":"F39","position":"39","formula":"(#{result5_q3}/#{target1_q3})*100","formula_old":"(,38,/,28,),*rate","digit_number":2,"number_format":1,"is_chart":0,"bgcolor":"#fbc198","sum_type":"SUM"},{"type":"N","position":"40","column_name":"target_q4","digit_number":0,"is_show":1,"is_chart":0,"sum_type":"SUM"},{"type":"N","position":"41","column_name":"target1_q4","digit_number":0,"is_show":1,"is_chart":0,"sum_type":"SUM"},{"type":"F","column_name":"F42","position":"42","formula":"(#{target1_q4}/#{target_q4})*100","formula_old":"(,41,/,40,),*rate","digit_number":2,"number_format":1,"is_chart":0,"bgcolor":"#98fbfa","sum_type":"SUM"},{"type":"N","position":"43","column_name":"result1_q4","digit_number":0,"is_show":1,"is_chart":0,"sum_type":"SUM"},{"type":"F","column_name":"F44","position":"44","formula":"(#{result1_q4}/#{target1_q4})*100","formula_old":"(,43,/,41,),*rate","digit_number":2,"number_format":1,"is_chart":0,"bgcolor":"#fbc198","sum_type":"SUM"},{"type":"N","position":"45","column_name":"result2_q4","digit_number":0,"is_show":1,"is_chart":0,"sum_type":"SUM"},{"type":"F","column_name":"F46","position":"46","formula":"(#{result2_q4}/#{target1_q4})*100","formula_old":"(,45,/,41,),*rate","digit_number":2,"number_format":1,"is_chart":0,"bgcolor":"#fbfa98","sum_type":"SUM"},{"type":"N","position":"47","column_name":"result3_q4","digit_number":0,"is_show":1,"is_chart":0,"sum_type":"SUM"},{"type":"F","column_name":"F48","position":"48","formula":"(#{result3_q4}/#{target1_q4})*100","formula_old":"(,47,/,41,),*rate","digit_number":2,"number_format":1,"is_chart":1,"bgcolor":"#50B432","sum_type":"SUM"},{"type":"N","position":"49","column_name":"result4_q4","digit_number":0,"is_show":1,"is_chart":0,"sum_type":"SUM"},{"type":"F","column_name":"F50","position":"50","formula":"(#{result4_q4}/#{target1_q4})*100","formula_old":"(,49,/,41,),*rate","digit_number":2,"number_format":1,"is_chart":0,"bgcolor":"#fbfa98","sum_type":"SUM"},{"type":"N","position":"51","column_name":"result5_q4","digit_number":0,"is_show":1,"is_chart":0,"sum_type":"SUM"},{"type":"F","column_name":"F52","position":"52","formula":"(#{result5_q4}/#{target1_q4})*100","formula_old":"(,51,/,41,),*rate","digit_number":2,"number_format":1,"is_chart":0,"bgcolor":"#fbc198","sum_type":"SUM"}],"data":[{"a_code":"02803","a_name":"02803:โรงพยาบาลส่งเสริมสุขภาพตำบลหนองมะค่า","target_q1":"81","target1_q1":"45","result1_q1":"3","result2_q1":"1","result3_q1":"34","result4_q1":"1","result5_q1":"5","target_q2":"71","target1_q2":"65","result1_q2":"12","result2_q2":"3","result3_q2":"44","result4_q2":"3","result5_q2":"0","target_q3":"68","target1_q3":"64","result1_q3":"1","result2_q3":"1","result3_q3":"46","result4_q3":"4","result5_q3":"10","target_q4":"64","target1_q4":"0","result1_q4":"0","result2_q4":"0","result3_q4":"0","result4_q4":"0","result5_q4":"0","F3":55.55555555555556,"F5":6.666666666666667,"F7":2.2222222222222223,"F9":75.55555555555556,"F11":2.2222222222222223,"F13":11.11111111111111,"F16":91.54929577464789,"F18":18.461538461538463,"F20":4.615384615384616,"F22":67.6923076923077,"F24":4.615384615384616,"F26":0,"F29":94.11764705882352,"F31":1.5625,"F33":1.5625,"F35":71.875,"F37":6.25,"F39":15.625,"F42":0,"F44":null,"F46":null,"F48":null,"F50":null,"F52":null},{"a_code":"02804","a_name":"02804:โรงพยาบาลส่งเสริมสุขภาพตำบลกลางดง","target_q1":"153","target1_q1":"125","result1_q1":"13","result2_q1":"5","result3_q1":"74","result4_q1":"7","result5_q1":"20","target_q2":"135","target1_q2":"122","result1_q2":"3","result2_q2":"3","result3_q2":"111","result4_q2":"2","result5_q2":"3","target_q3":"120","target1_q3":"117","result1_q3":"7","result2_q3":"2","result3_q3":"100","result4_q3":"2","result5_q3":"6","target_q4":"106","target1_q4":"0","result1_q4":"0","result2_q4":"0","result3_q4":"0","result4_q4":"0","result5_q4":"0","F3":81.69934640522875,"F5":10.4,"F7":4,"F9":59.199999999999996,"F11":5.6000000000000005,"F13":16,"F16":90.37037037037037,"F18":2.459016393442623,"F20":2.459016393442623,"F22":90.98360655737704,"F24":1.639344262295082,"F26":2.459016393442623,"F29":97.5,"F31":5.982905982905983,"F33":1.7094017094017095,"F35":85.47008547008546,"F37":1.7094017094017095,"F39":5.128205128205128,"F42":0,"F44":null,"F46":null,"F48":null,"F50":null,"F52":null},{"a_code":"02805","a_name":"02805:โรงพยาบาลส่งเสริมสุขภาพตำบลหนองกระทุ่ม","target_q1":"145","target1_q1":"128","result1_q1":"0","result2_q1":"5","result3_q1":"113","result4_q1":"5","result5_q1":"5","target_q2":"131","target1_q2":"116","result1_q2":"0","result2_q2":"2","result3_q2":"104","result4_q2":"4","result5_q2":"6","target_q3":"118","target1_q3":"39","result1_q3":"4","result2_q3":"1","result3_q3":"31","result4_q3":"2","result5_q3":"1","target_q4":"110","target1_q4":"0","result1_q4":"0","result2_q4":"0","result3_q4":"0","result4_q4":"0","result5_q4":"0","F3":88.27586206896552,"F5":0,"F7":3.90625,"F9":88.28125,"F11":3.90625,"F13":3.90625,"F16":88.54961832061069,"F18":0,"F20":1.7241379310344827,"F22":89.65517241379311,"F24":3.4482758620689653,"F26":5.172413793103448,"F29":33.05084745762712,"F31":10.256410256410255,"F33":2.564102564102564,"F35":79.48717948717949,"F37":5.128205128205128,"F39":2.564102564102564,"F42":0,"F44":null,"F46":null,"F48":null,"F50":null,"F52":null},{"a_code":"02806","a_name":"02806:โรงพยาบาลส่งเสริมสุขภาพตำบลหนองไข่น้ำ","target_q1":"74","target1_q1":"69","result1_q1":"3","result2_q1":"7","result3_q1":"54","result4_q1":"2","result5_q1":"3","target_q2":"72","target1_q2":"71","result1_q2":"0","result2_q2":"1","result3_q2":"69","result4_q2":"0","result5_q2":"1","target_q3":"69","target1_q3":"66","result1_q3":"0","result2_q3":"2","result3_q3":"64","result4_q3":"0","result5_q3":"0","target_q4":"60","target1_q4":"0","result1_q4":"0","result2_q4":"0","result3_q4":"0","result4_q4":"0","result5_q4":"0","F3":93.24324324324324,"F5":4.3478260869565215,"F7":10.144927536231885,"F9":78.26086956521739,"F11":2.898550724637681,"F13":4.3478260869565215,"F16":98.61111111111111,"F18":0,"F20":1.4084507042253522,"F22":97.1830985915493,"F24":0,"F26":1.4084507042253522,"F29":95.65217391304348,"F31":0,"F33":3.0303030303030303,"F35":96.96969696969697,"F37":0,"F39":0,"F42":0,"F44":null,"F46":null,"F48":null,"F50":null,"F52":null},{"a_code":"02807","a_name":"02807:โรงพยาบาลส่งเสริมสุขภาพตำบลวังกะทะ","target_q1":"18","target1_q1":"18","result1_q1":"0","result2_q1":"2","result3_q1":"16","result4_q1":"0","result5_q1":"0","target_q2":"20","target1_q2":"20","result1_q2":"1","result2_q2":"0","result3_q2":"19","result4_q2":"0","result5_q2":"0","target_q3":"21","target1_q3":"20","result1_q3":"0","result2_q3":"0","result3_q3":"20","result4_q3":"0","result5_q3":"0","target_q4":"20","target1_q4":"0","result1_q4":"0","result2_q4":"0","result3_q4":"0","result4_q4":"0","result5_q4":"0","F3":100,"F5":0,"F7":11.11111111111111,"F9":88.88888888888889,"F11":0,"F13":0,"F16":100,"F18":5,"F20":0,"F22":95,"F24":0,"F26":0,"F29":95.23809523809523,"F31":0,"F33":0,"F35":100,"F37":0,"F39":0,"F42":0,"F44":null,"F46":null,"F48":null,"F50":null,"F52":null},{"a_code":"02808","a_name":"02808:โรงพยาบาลส่งเสริมสุขภาพตำบลหนองขวาง","target_q1":"63","target1_q1":"59","result1_q1":"6","result2_q1":"2","result3_q1":"49","result4_q1":"1","result5_q1":"1","target_q2":"64","target1_q2":"57","result1_q2":"0","result2_q2":"0","result3_q2":"56","result4_q2":"1","result5_q2":"0","target_q3":"58","target1_q3":"54","result1_q3":"0","result2_q3":"0","result3_q3":"52","result4_q3":"1","result5_q3":"1","target_q4":"52","target1_q4":"0","result1_q4":"0","result2_q4":"0","result3_q4":"0","result4_q4":"0","result5_q4":"0","F3":93.65079365079364,"F5":10.16949152542373,"F7":3.389830508474576,"F9":83.05084745762711,"F11":1.694915254237288,"F13":1.694915254237288,"F16":89.0625,"F18":0,"F20":0,"F22":98.24561403508771,"F24":1.7543859649122806,"F26":0,"F29":93.10344827586206,"F31":0,"F33":0,"F35":96.29629629629629,"F37":1.8518518518518516,"F39":1.8518518518518516,"F42":0,"F44":null,"F46":null,"F48":null,"F50":null,"F52":null},{"a_code":"02809","a_name":"02809:โรงพยาบาลส่งเสริมสุขภาพตำบลคลองดินดำ","target_q1":"51","target1_q1":"38","result1_q1":"1","result2_q1":"0","result3_q1":"32","result4_q1":"3","result5_q1":"2","target_q2":"50","target1_q2":"47","result1_q2":"4","result2_q2":"2","result3_q2":"39","result4_q2":"1","result5_q2":"1","target_q3":"43","target1_q3":"24","result1_q3":"1","result2_q3":"3","result3_q3":"17","result4_q3":"3","result5_q3":"0","target_q4":"38","target1_q4":"0","result1_q4":"0","result2_q4":"0","result3_q4":"0","result4_q4":"0","result5_q4":"0","F3":74.50980392156863,"F5":2.631578947368421,"F7":0,"F9":84.21052631578947,"F11":7.894736842105263,"F13":5.263157894736842,"F16":94,"F18":8.51063829787234,"F20":4.25531914893617,"F22":82.97872340425532,"F24":2.127659574468085,"F26":2.127659574468085,"F29":55.81395348837209,"F31":4.166666666666666,"F33":12.5,"F35":70.83333333333334,"F37":12.5,"F39":0,"F42":0,"F44":null,"F46":null,"F48":null,"F50":null,"F52":null},{"a_code":"02810","a_name":"02810:โรงพยาบาลส่งเสริมสุขภาพตำบลท่าช้าง","target_q1":"39","target1_q1":"36","result1_q1":"1","result2_q1":"1","result3_q1":"29","result4_q1":"2","result5_q1":"3","target_q2":"36","target1_q2":"33","result1_q2":"2","result2_q2":"1","result3_q2":"28","result4_q2":"1","result5_q2":"1","target_q3":"33","target1_q3":"33","result1_q3":"0","result2_q3":"0","result3_q3":"32","result4_q3":"0","result5_q3":"0","target_q4":"32","target1_q4":"0","result1_q4":"0","result2_q4":"0","result3_q4":"0","result4_q4":"0","result5_q4":"0","F3":92.3076923076923,"F5":2.7777777777777777,"F7":2.7777777777777777,"F9":80.55555555555556,"F11":5.555555555555555,"F13":8.333333333333332,"F16":91.66666666666666,"F18":6.0606060606060606,"F20":3.0303030303030303,"F22":84.84848484848484,"F24":3.0303030303030303,"F26":3.0303030303030303,"F29":100,"F31":0,"F33":0,"F35":96.96969696969697,"F37":0,"F39":0,"F42":0,"F44":null,"F46":null,"F48":null,"F50":null,"F52":null},{"a_code":"02811","a_name":"02811:สถานีอนามัยเฉลิมพระเกียรติ 60 พรรษา นวมินทราชินี นิคมลำตะคอง","target_q1":"167","target1_q1":"146","result1_q1":"18","result2_q1":"12","result3_q1":"101","result4_q1":"6","result5_q1":"6","target_q2":"149","target1_q2":"139","result1_q2":"2","result2_q2":"3","result3_q2":"131","result4_q2":"2","result5_q2":"1","target_q3":"136","target1_q3":"126","result1_q3":"2","result2_q3":"8","result3_q3":"101","result4_q3":"7","result5_q3":"7","target_q4":"118","target1_q4":"0","result1_q4":"0","result2_q4":"0","result3_q4":"0","result4_q4":"0","result5_q4":"0","F3":87.42514970059881,"F5":12.32876712328767,"F7":8.21917808219178,"F9":69.17808219178082,"F11":4.10958904109589,"F13":4.10958904109589,"F16":93.28859060402685,"F18":1.4388489208633095,"F20":2.158273381294964,"F22":94.24460431654677,"F24":1.4388489208633095,"F26":0.7194244604316548,"F29":92.64705882352942,"F31":1.5873015873015872,"F33":6.349206349206349,"F35":80.15873015873017,"F37":5.555555555555555,"F39":5.555555555555555,"F42":0,"F44":null,"F46":null,"F48":null,"F50":null,"F52":null},{"a_code":"02812","a_name":"02812:โรงพยาบาลส่งเสริมสุขภาพตำบลบ่อทอง","target_q1":"141","target1_q1":"123","result1_q1":"0","result2_q1":"1","result3_q1":"121","result4_q1":"1","result5_q1":"0","target_q2":"138","target1_q2":"124","result1_q2":"8","result2_q2":"2","result3_q2":"111","result4_q2":"1","result5_q2":"1","target_q3":"124","target1_q3":"115","result1_q3":"9","result2_q3":"7","result3_q3":"97","result4_q3":"1","result5_q3":"0","target_q4":"113","target1_q4":"0","result1_q4":"0","result2_q4":"0","result3_q4":"0","result4_q4":"0","result5_q4":"0","F3":87.2340425531915,"F5":0,"F7":0.8130081300813009,"F9":98.3739837398374,"F11":0.8130081300813009,"F13":0,"F16":89.85507246376811,"F18":6.451612903225806,"F20":1.6129032258064515,"F22":89.51612903225806,"F24":0.8064516129032258,"F26":0.8064516129032258,"F29":92.74193548387096,"F31":7.82608695652174,"F33":6.086956521739131,"F35":84.34782608695653,"F37":0.8695652173913043,"F39":0,"F42":0,"F44":null,"F46":null,"F48":null,"F50":null,"F52":null},{"a_code":"02813","a_name":"02813:โรงพยาบาลส่งเสริมสุขภาพตำบลขนงพระเหนือ","target_q1":"98","target1_q1":"86","result1_q1":"2","result2_q1":"1","result3_q1":"78","result4_q1":"4","result5_q1":"1","target_q2":"88","target1_q2":"84","result1_q2":"2","result2_q2":"1","result3_q2":"77","result4_q2":"3","result5_q2":"1","target_q3":"81","target1_q3":"58","result1_q3":"1","result2_q3":"1","result3_q3":"50","result4_q3":"1","result5_q3":"5","target_q4":"70","target1_q4":"0","result1_q4":"0","result2_q4":"0","result3_q4":"0","result4_q4":"0","result5_q4":"0","F3":87.75510204081633,"F5":2.3255813953488373,"F7":1.1627906976744187,"F9":90.69767441860465,"F11":4.651162790697675,"F13":1.1627906976744187,"F16":95.45454545454545,"F18":2.380952380952381,"F20":1.1904761904761905,"F22":91.66666666666666,"F24":3.571428571428571,"F26":1.1904761904761905,"F29":71.60493827160494,"F31":1.7241379310344827,"F33":1.7241379310344827,"F35":86.20689655172413,"F37":1.7241379310344827,"F39":8.620689655172415,"F42":0,"F44":null,"F46":null,"F48":null,"F50":null,"F52":null},{"a_code":"02814","a_name":"02814:โรงพยาบาลส่งเสริมสุขภาพตำบลขนงพระใต้","target_q1":"85","target1_q1":"76","result1_q1":"2","result2_q1":"0","result3_q1":"69","result4_q1":"1","result5_q1":"3","target_q2":"77","target1_q2":"72","result1_q2":"7","result2_q2":"1","result3_q2":"59","result4_q2":"4","result5_q2":"0","target_q3":"70","target1_q3":"64","result1_q3":"2","result2_q3":"4","result3_q3":"55","result4_q3":"1","result5_q3":"2","target_q4":"63","target1_q4":"0","result1_q4":"0","result2_q4":"0","result3_q4":"0","result4_q4":"0","result5_q4":"0","F3":89.41176470588236,"F5":2.631578947368421,"F7":0,"F9":90.78947368421053,"F11":1.3157894736842104,"F13":3.9473684210526314,"F16":93.5064935064935,"F18":9.722222222222223,"F20":1.3888888888888888,"F22":81.94444444444444,"F24":5.555555555555555,"F26":0,"F29":91.42857142857143,"F31":3.125,"F33":6.25,"F35":85.9375,"F37":1.5625,"F39":3.125,"F42":0,"F44":null,"F46":null,"F48":null,"F50":null,"F52":null},{"a_code":"02815","a_name":"02815:โรงพยาบาลส่งเสริมสุขภาพตำบลหนองคุ้ม","target_q1":"46","target1_q1":"37","result1_q1":"1","result2_q1":"1","result3_q1":"30","result4_q1":"1","result5_q1":"3","target_q2":"42","target1_q2":"41","result1_q2":"0","result2_q2":"0","result3_q2":"36","result4_q2":"2","result5_q2":"3","target_q3":"40","target1_q3":"38","result1_q3":"0","result2_q3":"2","result3_q3":"31","result4_q3":"3","result5_q3":"2","target_q4":"34","target1_q4":"0","result1_q4":"0","result2_q4":"0","result3_q4":"0","result4_q4":"0","result5_q4":"0","F3":80.43478260869566,"F5":2.7027027027027026,"F7":2.7027027027027026,"F9":81.08108108108108,"F11":2.7027027027027026,"F13":8.108108108108109,"F16":97.61904761904762,"F18":0,"F20":0,"F22":87.8048780487805,"F24":4.878048780487805,"F26":7.317073170731707,"F29":95,"F31":0,"F33":5.263157894736842,"F35":81.57894736842105,"F37":7.894736842105263,"F39":5.263157894736842,"F42":0,"F44":null,"F46":null,"F48":null,"F50":null,"F52":null},{"a_code":"02816","a_name":"02816:โรงพยาบาลส่งเสริมสุขภาพตำบลคลองม่วง","target_q1":"93","target1_q1":"84","result1_q1":"1","result2_q1":"2","result3_q1":"79","result4_q1":"0","result5_q1":"2","target_q2":"88","target1_q2":"81","result1_q2":"2","result2_q2":"3","result3_q2":"72","result4_q2":"2","result5_q2":"2","target_q3":"77","target1_q3":"72","result1_q3":"2","result2_q3":"2","result3_q3":"67","result4_q3":"1","result5_q3":"0","target_q4":"69","target1_q4":"0","result1_q4":"0","result2_q4":"0","result3_q4":"0","result4_q4":"0","result5_q4":"0","F3":90.32258064516128,"F5":1.1904761904761905,"F7":2.380952380952381,"F9":94.04761904761905,"F11":0,"F13":2.380952380952381,"F16":92.04545454545455,"F18":2.4691358024691357,"F20":3.7037037037037033,"F22":88.88888888888889,"F24":2.4691358024691357,"F26":2.4691358024691357,"F29":93.5064935064935,"F31":2.7777777777777777,"F33":2.7777777777777777,"F35":93.05555555555556,"F37":1.3888888888888888,"F39":0,"F42":0,"F44":null,"F46":null,"F48":null,"F50":null,"F52":null},{"a_code":"02817","a_name":"02817:โรงพยาบาลส่งเสริมสุขภาพตำบลซับพลู","target_q1":"73","target1_q1":"47","result1_q1":"5","result2_q1":"3","result3_q1":"34","result4_q1":"4","result5_q1":"1","target_q2":"68","target1_q2":"61","result1_q2":"5","result2_q2":"6","result3_q2":"46","result4_q2":"2","result5_q2":"2","target_q3":"65","target1_q3":"64","result1_q3":"3","result2_q3":"3","result3_q3":"53","result4_q3":"1","result5_q3":"4","target_q4":"60","target1_q4":"0","result1_q4":"0","result2_q4":"0","result3_q4":"0","result4_q4":"0","result5_q4":"0","F3":64.38356164383562,"F5":10.638297872340425,"F7":6.382978723404255,"F9":72.3404255319149,"F11":8.51063829787234,"F13":2.127659574468085,"F16":89.70588235294117,"F18":8.19672131147541,"F20":9.836065573770492,"F22":75.40983606557377,"F24":3.278688524590164,"F26":3.278688524590164,"F29":98.46153846153847,"F31":4.6875,"F33":4.6875,"F35":82.8125,"F37":1.5625,"F39":6.25,"F42":0,"F44":null,"F46":null,"F48":null,"F50":null,"F52":null},{"a_code":"02818","a_name":"02818:โรงพยาบาลส่งเสริมสุขภาพตำบลหนองน้ำแดง","target_q1":"117","target1_q1":"104","result1_q1":"0","result2_q1":"0","result3_q1":"104","result4_q1":"0","result5_q1":"0","target_q2":"108","target1_q2":"105","result1_q2":"3","result2_q2":"7","result3_q2":"91","result4_q2":"1","result5_q2":"3","target_q3":"100","target1_q3":"100","result1_q3":"5","result2_q3":"2","result3_q3":"87","result4_q3":"2","result5_q3":"2","target_q4":"95","target1_q4":"0","result1_q4":"0","result2_q4":"0","result3_q4":"0","result4_q4":"0","result5_q4":"0","F3":88.88888888888889,"F5":0,"F7":0,"F9":100,"F11":0,"F13":0,"F16":97.22222222222221,"F18":2.857142857142857,"F20":6.666666666666667,"F22":86.66666666666667,"F24":0.9523809523809524,"F26":2.857142857142857,"F29":100,"F31":5,"F33":2,"F35":87,"F37":2,"F39":2,"F42":0,"F44":null,"F46":null,"F48":null,"F50":null,"F52":null},{"a_code":"02819","a_name":"02819:โรงพยาบาลส่งเสริมสุขภาพตำบลวังไทร","target_q1":"100","target1_q1":"91","result1_q1":"2","result2_q1":"3","result3_q1":"78","result4_q1":"4","result5_q1":"4","target_q2":"94","target1_q2":"76","result1_q2":"0","result2_q2":"5","result3_q2":"64","result4_q2":"4","result5_q2":"3","target_q3":"82","target1_q3":"81","result1_q3":"1","result2_q3":"5","result3_q3":"72","result4_q3":"0","result5_q3":"3","target_q4":"79","target1_q4":"0","result1_q4":"0","result2_q4":"0","result3_q4":"0","result4_q4":"0","result5_q4":"0","F3":91,"F5":2.197802197802198,"F7":3.296703296703297,"F9":85.71428571428571,"F11":4.395604395604396,"F13":4.395604395604396,"F16":80.85106382978722,"F18":0,"F20":6.578947368421052,"F22":84.21052631578947,"F24":5.263157894736842,"F26":3.9473684210526314,"F29":98.78048780487805,"F31":1.2345679012345678,"F33":6.172839506172839,"F35":88.88888888888889,"F37":0,"F39":3.7037037037037033,"F42":0,"F44":null,"F46":null,"F48":null,"F50":null,"F52":null},{"a_code":"02820","a_name":"02820:โรงพยาบาลส่งเสริมสุขภาพตำบลซับน้อย","target_q1":"51","target1_q1":"40","result1_q1":"2","result2_q1":"1","result3_q1":"33","result4_q1":"3","result5_q1":"1","target_q2":"48","target1_q2":"47","result1_q2":"1","result2_q2":"2","result3_q2":"41","result4_q2":"2","result5_q2":"1","target_q3":"46","target1_q3":"43","result1_q3":"0","result2_q3":"0","result3_q3":"42","result4_q3":"0","result5_q3":"1","target_q4":"41","target1_q4":"0","result1_q4":"0","result2_q4":"0","result3_q4":"0","result4_q4":"0","result5_q4":"0","F3":78.43137254901961,"F5":5,"F7":2.5,"F9":82.5,"F11":7.5,"F13":2.5,"F16":97.91666666666666,"F18":2.127659574468085,"F20":4.25531914893617,"F22":87.2340425531915,"F24":4.25531914893617,"F26":2.127659574468085,"F29":93.47826086956522,"F31":0,"F33":0,"F35":97.67441860465115,"F37":0,"F39":2.3255813953488373,"F42":0,"F44":null,"F46":null,"F48":null,"F50":null,"F52":null},{"a_code":"02821","a_name":"02821:โรงพยาบาลส่งเสริมสุขภาพตำบลโนนกระโดน","target_q1":"61","target1_q1":"59","result1_q1":"4","result2_q1":"3","result3_q1":"50","result4_q1":"0","result5_q1":"1","target_q2":"60","target1_q2":"59","result1_q2":"2","result2_q2":"2","result3_q2":"52","result4_q2":"1","result5_q2":"1","target_q3":"58","target1_q3":"55","result1_q3":"4","result2_q3":"0","result3_q3":"50","result4_q3":"1","result5_q3":"0","target_q4":"52","target1_q4":"0","result1_q4":"0","result2_q4":"0","result3_q4":"0","result4_q4":"0","result5_q4":"0","F3":96.72131147540983,"F5":6.779661016949152,"F7":5.084745762711865,"F9":84.7457627118644,"F11":0,"F13":1.694915254237288,"F16":98.33333333333333,"F18":3.389830508474576,"F20":3.389830508474576,"F22":88.13559322033898,"F24":1.694915254237288,"F26":1.694915254237288,"F29":94.82758620689656,"F31":7.2727272727272725,"F33":0,"F35":90.9090909090909,"F37":1.8181818181818181,"F39":0,"F42":0,"F44":null,"F46":null,"F48":null,"F50":null,"F52":null},{"a_code":"10890","a_name":"10890:โรงพยาบาลปากช่องนานา","target_q1":"93","target1_q1":"81","result1_q1":"2","result2_q1":"1","result3_q1":"72","result4_q1":"3","result5_q1":"2","target_q2":"85","target1_q2":"78","result1_q2":"1","result2_q2":"2","result3_q2":"65","result4_q2":"2","result5_q2":"6","target_q3":"78","target1_q3":"65","result1_q3":"1","result2_q3":"0","result3_q3":"59","result4_q3":"2","result5_q3":"2","target_q4":"69","target1_q4":"0","result1_q4":"0","result2_q4":"0","result3_q4":"0","result4_q4":"0","result5_q4":"0","F3":87.09677419354838,"F5":2.4691358024691357,"F7":1.2345679012345678,"F9":88.88888888888889,"F11":3.7037037037037033,"F13":2.4691358024691357,"F16":91.76470588235294,"F18":1.282051282051282,"F20":2.564102564102564,"F22":83.33333333333334,"F24":2.564102564102564,"F26":7.6923076923076925,"F29":83.33333333333334,"F31":1.5384615384615385,"F33":0,"F35":90.76923076923077,"F37":3.076923076923077,"F39":3.076923076923077,"F42":0,"F44":null,"F46":null,"F48":null,"F50":null,"F52":null},{"a_code":"14710","a_name":"14710:ศูนย์ควบคุมโรคติดต่อนำโดยแมลงที่ 5.4","target_q1":null,"target1_q1":null,"result1_q1":null,"result2_q1":null,"result3_q1":null,"result4_q1":null,"result5_q1":null,"target_q2":null,"target1_q2":null,"result1_q2":null,"result2_q2":null,"result3_q2":null,"result4_q2":null,"result5_q2":null,"target_q3":null,"target1_q3":null,"result1_q3":null,"result2_q3":null,"result3_q3":null,"result4_q3":null,"result5_q3":null,"target_q4":null,"target1_q4":null,"result1_q4":null,"result2_q4":null,"result3_q4":null,"result4_q4":null,"result5_q4":null,"F3":null,"F5":null,"F7":null,"F9":null,"F11":null,"F13":null,"F16":null,"F18":null,"F20":null,"F22":null,"F24":null,"F26":null,"F29":null,"F31":null,"F33":null,"F35":null,"F37":null,"F39":null,"F42":null,"F44":null,"F46":null,"F48":null,"F50":null,"F52":null},{"a_code":"23012","a_name":"23012:ศูนย์สุขภาพชุมชนเทศบาลเมืองปากช่อง3(หนองสาหร่าย)","target_q1":"118","target1_q1":"86","result1_q1":"11","result2_q1":"7","result3_q1":"63","result4_q1":"3","result5_q1":"1","target_q2":"115","target1_q2":"89","result1_q2":"5","result2_q2":"3","result3_q2":"74","result4_q2":"3","result5_q2":"3","target_q3":"106","target1_q3":"58","result1_q3":"13","result2_q3":"0","result3_q3":"41","result4_q3":"1","result5_q3":"2","target_q4":"93","target1_q4":"0","result1_q4":"0","result2_q4":"0","result3_q4":"0","result4_q4":"0","result5_q4":"0","F3":72.88135593220339,"F5":12.790697674418606,"F7":8.13953488372093,"F9":73.25581395348837,"F11":3.488372093023256,"F13":1.1627906976744187,"F16":77.39130434782608,"F18":5.617977528089887,"F20":3.3707865168539324,"F22":83.14606741573034,"F24":3.3707865168539324,"F26":3.3707865168539324,"F29":54.71698113207547,"F31":22.413793103448278,"F33":0,"F35":70.6896551724138,"F37":1.7241379310344827,"F39":3.4482758620689653,"F42":0,"F44":null,"F46":null,"F48":null,"F50":null,"F52":null},{"a_code":"24641","a_name":"24641:ศูนย์สุขภาพชุมชนเทศบาลเมืองปากช่อง 1","target_q1":"103","target1_q1":"85","result1_q1":"5","result2_q1":"2","result3_q1":"72","result4_q1":"3","result5_q1":"3","target_q2":"109","target1_q2":"107","result1_q2":"2","result2_q2":"2","result3_q2":"100","result4_q2":"0","result5_q2":"2","target_q3":"101","target1_q3":"53","result1_q3":"1","result2_q3":"1","result3_q3":"45","result4_q3":"1","result5_q3":"5","target_q4":"95","target1_q4":"0","result1_q4":"0","result2_q4":"0","result3_q4":"0","result4_q4":"0","result5_q4":"0","F3":82.52427184466019,"F5":5.88235294117647,"F7":2.3529411764705883,"F9":84.70588235294117,"F11":3.5294117647058822,"F13":3.5294117647058822,"F16":98.1651376146789,"F18":1.8691588785046727,"F20":1.8691588785046727,"F22":93.45794392523365,"F24":0,"F26":1.8691588785046727,"F29":52.475247524752476,"F31":1.8867924528301887,"F33":1.8867924528301887,"F35":84.90566037735849,"F37":1.8867924528301887,"F39":9.433962264150944,"F42":0,"F44":null,"F46":null,"F48":null,"F50":null,"F52":null},{"a_code":"24642","a_name":"24642:ศูนย์สุขภาพชุมชนเทศบาลเมืองปากช่อง 2","target_q1":"97","target1_q1":"92","result1_q1":"1","result2_q1":"3","result3_q1":"79","result4_q1":"1","result5_q1":"6","target_q2":"95","target1_q2":"92","result1_q2":"1","result2_q2":"1","result3_q2":"78","result4_q2":"4","result5_q2":"5","target_q3":"85","target1_q3":"81","result1_q3":"2","result2_q3":"1","result3_q3":"61","result4_q3":"7","result5_q3":"8","target_q4":"78","target1_q4":"0","result1_q4":"0","result2_q4":"0","result3_q4":"0","result4_q4":"0","result5_q4":"0","F3":94.84536082474226,"F5":1.0869565217391304,"F7":3.260869565217391,"F9":85.86956521739131,"F11":1.0869565217391304,"F13":6.521739130434782,"F16":96.84210526315789,"F18":1.0869565217391304,"F20":1.0869565217391304,"F22":84.78260869565217,"F24":4.3478260869565215,"F26":5.434782608695652,"F29":95.29411764705881,"F31":2.4691358024691357,"F33":1.2345679012345678,"F35":75.30864197530865,"F37":8.641975308641975,"F39":9.876543209876543,"F42":0,"F44":null,"F46":null,"F48":null,"F50":null,"F52":null},{"a_code":"54016","a_name":"54016:คลินิกเวชกรรมชุมชนอบอุ่นปากช่อง 1","target_q1":null,"target1_q1":null,"result1_q1":null,"result2_q1":null,"result3_q1":null,"result4_q1":null,"result5_q1":null,"target_q2":null,"target1_q2":null,"result1_q2":null,"result2_q2":null,"result3_q2":null,"result4_q2":null,"result5_q2":null,"target_q3":null,"target1_q3":null,"result1_q3":null,"result2_q3":null,"result3_q3":null,"result4_q3":null,"result5_q3":null,"target_q4":null,"target1_q4":null,"result1_q4":null,"result2_q4":null,"result3_q4":null,"result4_q4":null,"result5_q4":null,"F3":null,"F5":null,"F7":null,"F9":null,"F11":null,"F13":null,"F16":null,"F18":null,"F20":null,"F22":null,"F24":null,"F26":null,"F29":null,"F31":null,"F33":null,"F35":null,"F37":null,"F39":null,"F42":null,"F44":null,"F46":null,"F48":null,"F50":null,"F52":null},{"a_code":"77498","a_name":"77498:โรงพยาบาลมกุฏคีรีวัน","target_q1":"19","target1_q1":"12","result1_q1":"2","result2_q1":"2","result3_q1":"7","result4_q1":"0","result5_q1":"1","target_q2":"17","target1_q2":"15","result1_q2":"0","result2_q2":"1","result3_q2":"11","result4_q2":"2","result5_q2":"1","target_q3":"16","target1_q3":"10","result1_q3":"0","result2_q3":"1","result3_q3":"8","result4_q3":"0","result5_q3":"1","target_q4":"13","target1_q4":"0","result1_q4":"0","result2_q4":"0","result3_q4":"0","result4_q4":"0","result5_q4":"0","F3":63.1578947368421,"F5":16.666666666666664,"F7":16.666666666666664,"F9":58.333333333333336,"F11":0,"F13":8.333333333333332,"F16":88.23529411764706,"F18":0,"F20":6.666666666666667,"F22":73.33333333333333,"F24":13.333333333333334,"F26":6.666666666666667,"F29":62.5,"F31":0,"F33":10,"F35":80,"F37":0,"F39":10,"F42":0,"F44":null,"F46":null,"F48":null,"F50":null,"F52":null}],"datecom":"17 มิถุนายน 2569","source":1,"label":"หน่วยบริการ"}],"code":200}