{"ok":true,"rows":[{"jsonc":[{"position":0,"type":"C","column_name":"areaname"},{"position":1,"type":"N","column_name":"b","digit_number":"0","sum_type":"SUM"},{"position":2,"type":"N","column_name":"a","digit_number":"0"},{"position":3,"type":"F","column_name":"percent","formula":"(#{a}*100)/#{b}","digit_number":"2"},{"position":4,"type":"N","column_name":"b1","digit_number":"0"},{"position":5,"type":"N","column_name":"a1","digit_number":"0"},{"position":6,"type":"F","column_name":"percent1","formula":"(#{a1}*100)/#{b1}","digit_number":"2"},{"position":7,"type":"N","column_name":"b2","digit_number":"0"},{"position":8,"type":"N","column_name":"a2","digit_number":"0"},{"position":9,"type":"F","column_name":"percent2","formula":"(#{a2}*100)/#{b2}","digit_number":"2"},{"position":10,"type":"N","column_name":"b3","digit_number":"0"},{"position":11,"type":"N","column_name":"a3","digit_number":"0"},{"position":12,"type":"F","column_name":"percent3","formula":"(#{a3}*100)/#{b3}","digit_number":"2"},{"position":13,"type":"N","column_name":"b4","digit_number":"0"},{"position":14,"type":"N","column_name":"a4","digit_number":"0"},{"position":15,"type":"F","column_name":"percent4","formula":"(#{a4}*100)/#{b4}","digit_number":"2"}],"data":[{"hoscode":"02803","areaname":"โรงพยาบาลส่งเสริมสุขภาพตำบลหนองมะค่า","b":null,"a":null,"b1":null,"a1":null,"b2":null,"a2":null,"b3":null,"a3":null,"b4":null,"a4":null,"percent":null,"percent1":null,"percent2":null,"percent3":null,"percent4":null},{"hoscode":"02804","areaname":"โรงพยาบาลส่งเสริมสุขภาพตำบลกลางดง","b":null,"a":null,"b1":null,"a1":null,"b2":null,"a2":null,"b3":null,"a3":null,"b4":null,"a4":null,"percent":null,"percent1":null,"percent2":null,"percent3":null,"percent4":null},{"hoscode":"02805","areaname":"โรงพยาบาลส่งเสริมสุขภาพตำบลหนองกระทุ่ม","b":null,"a":null,"b1":null,"a1":null,"b2":null,"a2":null,"b3":null,"a3":null,"b4":null,"a4":null,"percent":null,"percent1":null,"percent2":null,"percent3":null,"percent4":null},{"hoscode":"02806","areaname":"โรงพยาบาลส่งเสริมสุขภาพตำบลหนองไข่น้ำ","b":366,"a":4,"b1":7,"a1":2,"b2":345,"a2":1,"b3":14,"a3":1,"b4":0,"a4":0,"percent":1.092896174863388,"percent1":28.571428571428573,"percent2":0.2898550724637681,"percent3":7.142857142857143,"percent4":null},{"hoscode":"02807","areaname":"โรงพยาบาลส่งเสริมสุขภาพตำบลวังกะทะ","b":148,"a":2,"b1":112,"a1":0,"b2":36,"a2":2,"b3":0,"a3":0,"b4":0,"a4":0,"percent":1.3513513513513513,"percent1":0,"percent2":5.555555555555555,"percent3":null,"percent4":null},{"hoscode":"02808","areaname":"โรงพยาบาลส่งเสริมสุขภาพตำบลหนองขวาง","b":null,"a":null,"b1":null,"a1":null,"b2":null,"a2":null,"b3":null,"a3":null,"b4":null,"a4":null,"percent":null,"percent1":null,"percent2":null,"percent3":null,"percent4":null},{"hoscode":"02809","areaname":"โรงพยาบาลส่งเสริมสุขภาพตำบลคลองดินดำ","b":null,"a":null,"b1":null,"a1":null,"b2":null,"a2":null,"b3":null,"a3":null,"b4":null,"a4":null,"percent":null,"percent1":null,"percent2":null,"percent3":null,"percent4":null},{"hoscode":"02810","areaname":"โรงพยาบาลส่งเสริมสุขภาพตำบลท่าช้าง","b":null,"a":null,"b1":null,"a1":null,"b2":null,"a2":null,"b3":null,"a3":null,"b4":null,"a4":null,"percent":null,"percent1":null,"percent2":null,"percent3":null,"percent4":null},{"hoscode":"02811","areaname":"สถานีอนามัยเฉลิมพระเกียรติ 60 พรรษา นวมินทราชินี นิคมลำตะคอง","b":null,"a":null,"b1":null,"a1":null,"b2":null,"a2":null,"b3":null,"a3":null,"b4":null,"a4":null,"percent":null,"percent1":null,"percent2":null,"percent3":null,"percent4":null},{"hoscode":"02812","areaname":"โรงพยาบาลส่งเสริมสุขภาพตำบลบ่อทอง","b":null,"a":null,"b1":null,"a1":null,"b2":null,"a2":null,"b3":null,"a3":null,"b4":null,"a4":null,"percent":null,"percent1":null,"percent2":null,"percent3":null,"percent4":null},{"hoscode":"02813","areaname":"โรงพยาบาลส่งเสริมสุขภาพตำบลขนงพระเหนือ","b":344,"a":2,"b1":104,"a1":0,"b2":217,"a2":1,"b3":23,"a3":1,"b4":0,"a4":0,"percent":0.5813953488372093,"percent1":0,"percent2":0.4608294930875576,"percent3":4.3478260869565215,"percent4":null},{"hoscode":"02814","areaname":"โรงพยาบาลส่งเสริมสุขภาพตำบลขนงพระใต้","b":439,"a":3,"b1":6,"a1":0,"b2":351,"a2":1,"b3":82,"a3":2,"b4":0,"a4":0,"percent":0.683371298405467,"percent1":0,"percent2":0.2849002849002849,"percent3":2.4390243902439024,"percent4":null},{"hoscode":"02815","areaname":"โรงพยาบาลส่งเสริมสุขภาพตำบลหนองคุ้ม","b":null,"a":null,"b1":null,"a1":null,"b2":null,"a2":null,"b3":null,"a3":null,"b4":null,"a4":null,"percent":null,"percent1":null,"percent2":null,"percent3":null,"percent4":null},{"hoscode":"02816","areaname":"โรงพยาบาลส่งเสริมสุขภาพตำบลคลองม่วง","b":568,"a":3,"b1":185,"a1":1,"b2":371,"a2":2,"b3":12,"a3":0,"b4":0,"a4":0,"percent":0.528169014084507,"percent1":0.5405405405405406,"percent2":0.5390835579514824,"percent3":0,"percent4":null},{"hoscode":"02817","areaname":"โรงพยาบาลส่งเสริมสุขภาพตำบลซับพลู","b":466,"a":6,"b1":243,"a1":3,"b2":211,"a2":3,"b3":12,"a3":0,"b4":0,"a4":0,"percent":1.2875536480686696,"percent1":1.2345679012345678,"percent2":1.4218009478672986,"percent3":0,"percent4":null},{"hoscode":"02818","areaname":"โรงพยาบาลส่งเสริมสุขภาพตำบลหนองน้ำแดง","b":null,"a":null,"b1":null,"a1":null,"b2":null,"a2":null,"b3":null,"a3":null,"b4":null,"a4":null,"percent":null,"percent1":null,"percent2":null,"percent3":null,"percent4":null},{"hoscode":"02819","areaname":"โรงพยาบาลส่งเสริมสุขภาพตำบลวังไทร","b":605,"a":7,"b1":307,"a1":7,"b2":220,"a2":0,"b3":78,"a3":0,"b4":0,"a4":0,"percent":1.1570247933884297,"percent1":2.2801302931596092,"percent2":0,"percent3":0,"percent4":null},{"hoscode":"02820","areaname":"โรงพยาบาลส่งเสริมสุขภาพตำบลซับน้อย","b":null,"a":null,"b1":null,"a1":null,"b2":null,"a2":null,"b3":null,"a3":null,"b4":null,"a4":null,"percent":null,"percent1":null,"percent2":null,"percent3":null,"percent4":null},{"hoscode":"02821","areaname":"โรงพยาบาลส่งเสริมสุขภาพตำบลโนนกระโดน","b":null,"a":null,"b1":null,"a1":null,"b2":null,"a2":null,"b3":null,"a3":null,"b4":null,"a4":null,"percent":null,"percent1":null,"percent2":null,"percent3":null,"percent4":null},{"hoscode":"10890","areaname":"โรงพยาบาลปากช่องนานา","b":26726,"a":1347,"b1":8927,"a1":378,"b2":10620,"a2":490,"b3":7134,"a3":477,"b4":45,"a4":2,"percent":5.040035920077827,"percent1":4.2343452447630785,"percent2":4.613935969868173,"percent3":6.6862910008410426,"percent4":4.444444444444445},{"hoscode":"14710","areaname":"ศูนย์ควบคุมโรคติดต่อนำโดยแมลงที่ 5.4","b":null,"a":null,"b1":null,"a1":null,"b2":null,"a2":null,"b3":null,"a3":null,"b4":null,"a4":null,"percent":null,"percent1":null,"percent2":null,"percent3":null,"percent4":null},{"hoscode":"23012","areaname":"ศูนย์สุขภาพชุมชนเทศบาลเมืองปากช่อง3(หนองสาหร่าย)","b":517,"a":3,"b1":158,"a1":0,"b2":313,"a2":0,"b3":46,"a3":3,"b4":0,"a4":0,"percent":0.5802707930367504,"percent1":0,"percent2":0,"percent3":6.521739130434782,"percent4":null},{"hoscode":"24641","areaname":"ศูนย์สุขภาพชุมชนเทศบาลเมืองปากช่อง 1","b":383,"a":1,"b1":372,"a1":0,"b2":0,"a2":0,"b3":11,"a3":1,"b4":0,"a4":0,"percent":0.26109660574412535,"percent1":0,"percent2":null,"percent3":9.090909090909092,"percent4":null},{"hoscode":"24642","areaname":"ศูนย์สุขภาพชุมชนเทศบาลเมืองปากช่อง 2","b":881,"a":5,"b1":321,"a1":0,"b2":525,"a2":3,"b3":35,"a3":2,"b4":0,"a4":0,"percent":0.5675368898978433,"percent1":0,"percent2":0.5714285714285714,"percent3":5.714285714285714,"percent4":null},{"hoscode":"54016","areaname":"คลินิกเวชกรรมชุมชนอบอุ่นปากช่อง 1","b":null,"a":null,"b1":null,"a1":null,"b2":null,"a2":null,"b3":null,"a3":null,"b4":null,"a4":null,"percent":null,"percent1":null,"percent2":null,"percent3":null,"percent4":null},{"hoscode":"77498","areaname":"โรงพยาบาลมกุฏคีรีวัน","b":3463,"a":75,"b1":1208,"a1":44,"b2":1699,"a2":24,"b3":556,"a3":7,"b4":0,"a4":0,"percent":2.165752237943979,"percent1":3.642384105960265,"percent2":1.412595644496763,"percent3":1.2589928057553956,"percent4":null}],"datecom":"09 กรกฎาคม 2569","source":1,"label":"หน่วยบริการ"}],"code":200}