{"ok":true,"rows":[{"jsonc":[{"type":"C","position":"0","column_name":"a_name"},{"type":"N","position":"1","column_name":"target1","digit_number":0,"is_show":1,"is_chart":0,"sum_type":"SUM"},{"type":"N","position":"2","column_name":"target","digit_number":0,"is_show":1,"is_chart":0,"sum_type":"SUM"},{"type":"F","column_name":"F3","position":"3","formula":"(#{target}/#{target1})*100","formula_old":"(,2,/,1,)*rate","digit_number":2,"number_format":1,"is_chart":0,"sum_type":"SUM"},{"type":"N","position":"4","column_name":"result","digit_number":0,"is_show":1,"is_chart":0,"sum_type":"SUM"},{"type":"F","column_name":"F5","position":"5","formula":"(#{result}/#{target})*100","formula_old":"(,4,/,2,)*rate","digit_number":2,"number_format":1,"is_chart":1,"sum_type":"SUM"}],"data":[{"a_code":"02803","a_name":"02803:โรงพยาบาลส่งเสริมสุขภาพตำบลหนองมะค่า","target":"2515","target1":"4871","result":"1811","F3":51.632108396633136,"F5":72.0079522862823},{"a_code":"02804","a_name":"02804:โรงพยาบาลส่งเสริมสุขภาพตำบลกลางดง","target":"3006","target1":"5921","result":"2615","F3":50.76845127512245,"F5":86.99268130405855},{"a_code":"02805","a_name":"02805:โรงพยาบาลส่งเสริมสุขภาพตำบลหนองกระทุ่ม","target":"2337","target1":"4236","result":"301","F3":55.169971671388105,"F5":12.879760376551133},{"a_code":"02806","a_name":"02806:โรงพยาบาลส่งเสริมสุขภาพตำบลหนองไข่น้ำ","target":"1325","target1":"2221","result":"586","F3":59.65781179648807,"F5":44.22641509433962},{"a_code":"02807","a_name":"02807:โรงพยาบาลส่งเสริมสุขภาพตำบลวังกะทะ","target":"1164","target1":"2046","result":"1134","F3":56.89149560117303,"F5":97.42268041237114},{"a_code":"02808","a_name":"02808:โรงพยาบาลส่งเสริมสุขภาพตำบลหนองขวาง","target":"1082","target1":"1475","result":"272","F3":73.35593220338983,"F5":25.13863216266174},{"a_code":"02809","a_name":"02809:โรงพยาบาลส่งเสริมสุขภาพตำบลคลองดินดำ","target":"1216","target1":"2018","result":"612","F3":60.257680872150644,"F5":50.32894736842105},{"a_code":"02810","a_name":"02810:โรงพยาบาลส่งเสริมสุขภาพตำบลท่าช้าง","target":"2023","target1":"3503","result":"1388","F3":57.7504995717956,"F5":68.61097380128523},{"a_code":"02811","a_name":"02811:สถานีอนามัยเฉลิมพระเกียรติ 60 พรรษา นวมินทราชินี นิคมลำตะคอง","target":"2710","target1":"5706","result":"2253","F3":47.493866105853485,"F5":83.13653136531364},{"a_code":"02812","a_name":"02812:โรงพยาบาลส่งเสริมสุขภาพตำบลบ่อทอง","target":"2877","target1":"5307","result":"2324","F3":54.21141888072357,"F5":80.7785888077859},{"a_code":"02813","a_name":"02813:โรงพยาบาลส่งเสริมสุขภาพตำบลขนงพระเหนือ","target":"1113","target1":"1808","result":"709","F3":61.559734513274336,"F5":63.701707097933514},{"a_code":"02814","a_name":"02814:โรงพยาบาลส่งเสริมสุขภาพตำบลขนงพระใต้","target":"1975","target1":"3455","result":"1202","F3":57.16353111432706,"F5":60.86075949367089},{"a_code":"02815","a_name":"02815:โรงพยาบาลส่งเสริมสุขภาพตำบลหนองคุ้ม","target":"971","target1":"1586","result":"515","F3":61.22320302648171,"F5":53.03810504634397},{"a_code":"02816","a_name":"02816:โรงพยาบาลส่งเสริมสุขภาพตำบลคลองม่วง","target":"1468","target1":"2315","result":"727","F3":63.41252699784017,"F5":49.52316076294278},{"a_code":"02817","a_name":"02817:โรงพยาบาลส่งเสริมสุขภาพตำบลซับพลู","target":"936","target1":"1574","result":"529","F3":59.46632782719187,"F5":56.51709401709402},{"a_code":"02818","a_name":"02818:โรงพยาบาลส่งเสริมสุขภาพตำบลหนองน้ำแดง","target":"2588","target1":"4711","result":"1670","F3":54.93525790702611,"F5":64.52859350850078},{"a_code":"02819","a_name":"02819:โรงพยาบาลส่งเสริมสุขภาพตำบลวังไทร","target":"1386","target1":"2339","result":"805","F3":59.25609234715691,"F5":58.080808080808076},{"a_code":"02820","a_name":"02820:โรงพยาบาลส่งเสริมสุขภาพตำบลซับน้อย","target":"1211","target1":"2503","result":"948","F3":48.381941669996,"F5":78.2824112303881},{"a_code":"02821","a_name":"02821:โรงพยาบาลส่งเสริมสุขภาพตำบลโนนกระโดน","target":"1589","target1":"3053","result":"779","F3":52.047166721257774,"F5":49.02454373820013},{"a_code":"10890","a_name":"10890:โรงพยาบาลปากช่องนานา","target":"3469","target1":"5937","result":"3198","F3":58.43018359440795,"F5":92.18795041798789},{"a_code":"14710","a_name":"14710:ศูนย์ควบคุมโรคติดต่อนำโดยแมลงที่ 5.4","target":null,"target1":null,"result":null,"F3":null,"F5":null},{"a_code":"23012","a_name":"23012:ศูนย์สุขภาพชุมชนเทศบาลเมืองปากช่อง3(หนองสาหร่าย)","target":"3257","target1":"5767","result":"3100","F3":56.47650424830935,"F5":95.17961314092723},{"a_code":"24641","a_name":"24641:ศูนย์สุขภาพชุมชนเทศบาลเมืองปากช่อง 1","target":"3105","target1":"5672","result":"2924","F3":54.7425952045134,"F5":94.170692431562},{"a_code":"24642","a_name":"24642:ศูนย์สุขภาพชุมชนเทศบาลเมืองปากช่อง 2","target":"2942","target1":"5229","result":"1731","F3":56.26314782941289,"F5":58.837525492862},{"a_code":"54016","a_name":"54016:คลินิกเวชกรรมชุมชนอบอุ่นปากช่อง 1","target":null,"target1":null,"result":null,"F3":null,"F5":null},{"a_code":"77498","a_name":"77498:โรงพยาบาลมกุฏคีรีวัน","target":"218","target1":"479","result":"94","F3":45.51148225469729,"F5":43.11926605504588}],"datecom":"17 มิถุนายน 2569","source":1,"label":"หน่วยบริการ"}],"code":200}