{"ok":true,"rows":[{"jsonc":[{"type":"C","position":"0","column_name":"a_name"},{"type":"N","position":"1","column_name":"result","digit_number":0,"is_show":1,"is_chart":1,"sum_type":"SUM"},{"type":"N","position":"2","column_name":"m10","digit_number":0,"is_show":1,"is_chart":0,"sum_type":"SUM"},{"type":"N","position":"3","column_name":"m11","digit_number":0,"is_show":1,"is_chart":0,"sum_type":"SUM"},{"type":"N","position":"4","column_name":"m12","digit_number":0,"is_show":1,"is_chart":0,"sum_type":"SUM"},{"type":"N","position":"5","column_name":"m01","digit_number":0,"is_show":1,"is_chart":0,"sum_type":"SUM"},{"type":"N","position":"6","column_name":"m02","digit_number":0,"is_show":1,"is_chart":0,"sum_type":"SUM"},{"type":"N","position":"7","column_name":"m03","digit_number":0,"is_show":1,"is_chart":0,"sum_type":"SUM"},{"type":"N","position":"8","column_name":"m04","digit_number":0,"is_show":1,"is_chart":0,"sum_type":"SUM"},{"type":"N","position":"9","column_name":"m05","digit_number":0,"is_show":1,"is_chart":0,"sum_type":"SUM"},{"type":"N","position":"10","column_name":"m06","digit_number":0,"is_show":1,"is_chart":0,"sum_type":"SUM"},{"type":"N","position":"11","column_name":"m07","digit_number":0,"is_show":1,"is_chart":0,"sum_type":"SUM"},{"type":"N","position":"12","column_name":"m08","digit_number":0,"is_show":1,"is_chart":0,"sum_type":"SUM"},{"type":"N","position":"13","column_name":"m09","digit_number":0,"is_show":1,"is_chart":0,"sum_type":"SUM"}],"data":[{"a_code":"02803","a_name":"02803:โรงพยาบาลส่งเสริมสุขภาพตำบลหนองมะค่า","result":"81","m10":"10","m11":"11","m12":"10","m01":"14","m02":"7","m03":"8","m04":"9","m05":"10","m06":"2","m07":"0","m08":"0","m09":"0"},{"a_code":"02804","a_name":"02804:โรงพยาบาลส่งเสริมสุขภาพตำบลกลางดง","result":"38","m10":"6","m11":"2","m12":"5","m01":"0","m02":"1","m03":"10","m04":"7","m05":"7","m06":"0","m07":"0","m08":"0","m09":"0"},{"a_code":"02805","a_name":"02805:โรงพยาบาลส่งเสริมสุขภาพตำบลหนองกระทุ่ม","result":null,"m10":null,"m11":null,"m12":null,"m01":null,"m02":null,"m03":null,"m04":null,"m05":null,"m06":null,"m07":null,"m08":null,"m09":null},{"a_code":"02806","a_name":"02806:โรงพยาบาลส่งเสริมสุขภาพตำบลหนองไข่น้ำ","result":"10","m10":"0","m11":"2","m12":"4","m01":"0","m02":"0","m03":"2","m04":"0","m05":"2","m06":"0","m07":"0","m08":"0","m09":"0"},{"a_code":"02807","a_name":"02807:โรงพยาบาลส่งเสริมสุขภาพตำบลวังกะทะ","result":null,"m10":null,"m11":null,"m12":null,"m01":null,"m02":null,"m03":null,"m04":null,"m05":null,"m06":null,"m07":null,"m08":null,"m09":null},{"a_code":"02808","a_name":"02808:โรงพยาบาลส่งเสริมสุขภาพตำบลหนองขวาง","result":"85","m10":"14","m11":"8","m12":"7","m01":"8","m02":"14","m03":"9","m04":"14","m05":"6","m06":"5","m07":"0","m08":"0","m09":"0"},{"a_code":"02809","a_name":"02809:โรงพยาบาลส่งเสริมสุขภาพตำบลคลองดินดำ","result":"106","m10":"8","m11":"15","m12":"15","m01":"7","m02":"21","m03":"18","m04":"12","m05":"10","m06":"0","m07":"0","m08":"0","m09":"0"},{"a_code":"02810","a_name":"02810:โรงพยาบาลส่งเสริมสุขภาพตำบลท่าช้าง","result":"150","m10":"17","m11":"15","m12":"45","m01":"9","m02":"12","m03":"24","m04":"15","m05":"10","m06":"3","m07":"0","m08":"0","m09":"0"},{"a_code":"02811","a_name":"02811:สถานีอนามัยเฉลิมพระเกียรติ 60 พรรษา นวมินทราชินี นิคมลำตะคอง","result":"174","m10":"43","m11":"15","m12":"23","m01":"14","m02":"14","m03":"24","m04":"22","m05":"16","m06":"3","m07":"0","m08":"0","m09":"0"},{"a_code":"02812","a_name":"02812:โรงพยาบาลส่งเสริมสุขภาพตำบลบ่อทอง","result":null,"m10":null,"m11":null,"m12":null,"m01":null,"m02":null,"m03":null,"m04":null,"m05":null,"m06":null,"m07":null,"m08":null,"m09":null},{"a_code":"02813","a_name":"02813:โรงพยาบาลส่งเสริมสุขภาพตำบลขนงพระเหนือ","result":"18","m10":"6","m11":"0","m12":"2","m01":"1","m02":"1","m03":"1","m04":"7","m05":"0","m06":"0","m07":"0","m08":"0","m09":"0"},{"a_code":"02814","a_name":"02814:โรงพยาบาลส่งเสริมสุขภาพตำบลขนงพระใต้","result":"58","m10":"13","m11":"0","m12":"3","m01":"8","m02":"7","m03":"7","m04":"9","m05":"10","m06":"1","m07":"0","m08":"0","m09":"0"},{"a_code":"02815","a_name":"02815:โรงพยาบาลส่งเสริมสุขภาพตำบลหนองคุ้ม","result":"21","m10":"4","m11":"3","m12":"4","m01":"1","m02":"2","m03":"3","m04":"3","m05":"0","m06":"1","m07":"0","m08":"0","m09":"0"},{"a_code":"02816","a_name":"02816:โรงพยาบาลส่งเสริมสุขภาพตำบลคลองม่วง","result":"74","m10":"13","m11":"7","m12":"21","m01":"5","m02":"8","m03":"13","m04":"5","m05":"0","m06":"2","m07":"0","m08":"0","m09":"0"},{"a_code":"02817","a_name":"02817:โรงพยาบาลส่งเสริมสุขภาพตำบลซับพลู","result":"10","m10":"0","m11":"0","m12":"0","m01":"0","m02":"2","m03":"3","m04":"5","m05":"0","m06":"0","m07":"0","m08":"0","m09":"0"},{"a_code":"02818","a_name":"02818:โรงพยาบาลส่งเสริมสุขภาพตำบลหนองน้ำแดง","result":"198","m10":"41","m11":"27","m12":"26","m01":"9","m02":"24","m03":"19","m04":"26","m05":"26","m06":"0","m07":"0","m08":"0","m09":"0"},{"a_code":"02819","a_name":"02819:โรงพยาบาลส่งเสริมสุขภาพตำบลวังไทร","result":"34","m10":"5","m11":"4","m12":"5","m01":"5","m02":"2","m03":"0","m04":"5","m05":"5","m06":"3","m07":"0","m08":"0","m09":"0"},{"a_code":"02820","a_name":"02820:โรงพยาบาลส่งเสริมสุขภาพตำบลซับน้อย","result":null,"m10":null,"m11":null,"m12":null,"m01":null,"m02":null,"m03":null,"m04":null,"m05":null,"m06":null,"m07":null,"m08":null,"m09":null},{"a_code":"02821","a_name":"02821:โรงพยาบาลส่งเสริมสุขภาพตำบลโนนกระโดน","result":"50","m10":"9","m11":"7","m12":"3","m01":"3","m02":"5","m03":"6","m04":"13","m05":"2","m06":"2","m07":"0","m08":"0","m09":"0"},{"a_code":"10890","a_name":"10890:โรงพยาบาลปากช่องนานา","result":"2376","m10":"321","m11":"290","m12":"285","m01":"264","m02":"276","m03":"271","m04":"292","m05":"296","m06":"81","m07":"0","m08":"0","m09":"0"},{"a_code":"14710","a_name":"14710:ศูนย์ควบคุมโรคติดต่อนำโดยแมลงที่ 5.4","result":null,"m10":null,"m11":null,"m12":null,"m01":null,"m02":null,"m03":null,"m04":null,"m05":null,"m06":null,"m07":null,"m08":null,"m09":null},{"a_code":"23012","a_name":"23012:ศูนย์สุขภาพชุมชนเทศบาลเมืองปากช่อง3(หนองสาหร่าย)","result":"121","m10":"16","m11":"6","m12":"15","m01":"4","m02":"34","m03":"16","m04":"7","m05":"17","m06":"6","m07":"0","m08":"0","m09":"0"},{"a_code":"24641","a_name":"24641:ศูนย์สุขภาพชุมชนเทศบาลเมืองปากช่อง 1","result":"5","m10":"0","m11":"0","m12":"0","m01":"0","m02":"2","m03":"3","m04":"0","m05":"0","m06":"0","m07":"0","m08":"0","m09":"0"},{"a_code":"24642","a_name":"24642:ศูนย์สุขภาพชุมชนเทศบาลเมืองปากช่อง 2","result":"118","m10":"19","m11":"5","m12":"25","m01":"4","m02":"17","m03":"20","m04":"15","m05":"13","m06":"0","m07":"0","m08":"0","m09":"0"},{"a_code":"54016","a_name":"54016:คลินิกเวชกรรมชุมชนอบอุ่นปากช่อง 1","result":null,"m10":null,"m11":null,"m12":null,"m01":null,"m02":null,"m03":null,"m04":null,"m05":null,"m06":null,"m07":null,"m08":null,"m09":null},{"a_code":"77498","a_name":"77498:โรงพยาบาลมกุฏคีรีวัน","result":"179","m10":"22","m11":"28","m12":"21","m01":"19","m02":"10","m03":"26","m04":"16","m05":"32","m06":"5","m07":"0","m08":"0","m09":"0"}],"datecom":"17 มิถุนายน 2569","source":1,"label":"หน่วยบริการ"}],"code":200}